flake8_future_annotations/__init__.py
flake8_future_annotations/checker.py
flake8_future_annotations/py.typed
tests/__init__.py
tests/conftest.py
tests/test_checker.py
tests/test_files/__init__.py
tests/test_files/edge_case.py
tests/test_files/from_typing_import.py
tests/test_files/import_typing.py
tests/test_files/import_typing_as.py
tests/test_files/no_future_import_uses_lowercase.py
tests/test_files/no_future_import_uses_union.py
tests/test_files/no_future_import_uses_union_inner.py
tests/test_files/ok_no_types.py
tests/test_files/ok_non_simplifiable_types.py
tests/test_files/ok_uses_future.py
tests/test_files/ok_variable_name.py
flake8_future_annotations-1.1.0.dist-info/LICENSE
flake8_future_annotations-1.1.0.dist-info/METADATA
flake8_future_annotations-1.1.0.dist-info/WHEEL
flake8_future_annotations-1.1.0.dist-info/entry_points.txt
flake8_future_annotations-1.1.0.dist-info/top_level.txt
flake8_future_annotations-1.1.0.dist-info/RECORD
